prune_code/__init__.py
prune_code/__main__.py
prune_code/cli.py
prune_code/config.py
prune_code/distiller.py
prune_code/logging_utils.py
prune_code/sampling.py
prune_code-2.0.4.dist-info/METADATA
prune_code-2.0.4.dist-info/WHEEL
prune_code-2.0.4.dist-info/entry_points.txt
prune_code-2.0.4.dist-info/licenses/LICENSE
prune_code-2.0.4.dist-info/RECORD
