Metadata-Version: 2.4
Name: prune-code
Version: 2.0.4
Summary: Create filtered, context-optimized copies of repositories for LLM-friendly context engineering.
Project-URL: Homepage, https://github.com/jon-chun/prune-code
Project-URL: Repository, https://github.com/jon-chun/prune-code
Project-URL: Issues, https://github.com/jon-chun/prune-code/issues
Author: Jon Chun
License: MIT License
License-File: LICENSE
Keywords: cli,context,distill,filter,llm,repository,sampling
Classifier: Development Status :: 4 - Beta
Classifier: Intended Audience :: Developers
Classifier: License :: OSI Approved :: MIT License
Classifier: Programming Language :: Python :: 3
Classifier: Programming Language :: Python :: 3 :: Only
Classifier: Programming Language :: Python :: 3.8
Classifier: Programming Language :: Python :: 3.9
Classifier: Programming Language :: Python :: 3.10
Classifier: Programming Language :: Python :: 3.11
Classifier: Programming Language :: Python :: 3.12
Classifier: Topic :: Software Development :: Build Tools
Classifier: Topic :: Utilities
Requires-Python: >=3.8
Requires-Dist: build>=1.2.2.post1
Requires-Dist: pyyaml>=6.0
Requires-Dist: twine>=6.1.0
Provides-Extra: dev
Requires-Dist: pytest>=7.0; extra == 'dev'
Provides-Extra: docs
Requires-Dist: mkdocs-material>=9.7.0; extra == 'docs'
Requires-Dist: mkdocs>=1.6.1; extra == 'docs'
Requires-Dist: mkdocstrings[python]>=0.26.1; extra == 'docs'
